repo_ingestor/__init__.py
repo_ingestor/__main__.py
repo_ingestor/cli.py
repo_ingestor/config.py
repo_ingestor/core.py
repo_ingestor/formatters.py
repo_ingestor/function_analyzer.py
repo_ingestor/token_utils.py
repo_ingestor/utils.py
repo_ingestor/language_handlers/__init__.py
repo_ingestor/language_handlers/base.py
repo_ingestor/language_handlers/csharp.py
repo_ingestor/language_handlers/python.py
repo_ingestor/language_handlers/react.py
tests/__init__.py
tests/fixtures.py
tests/test_cli.py
tests/test_config.py
tests/test_core.py
tests/test_formatters.py
tests/test_function_analyzer.py
tests/test_token_utils.py
tests/test_utils.py
tests/test_language_handlers/__init__.py
tests/test_language_handlers/test_csharp.py
tests/test_language_handlers/test_python.py
tests/test_language_handlers/test_react.py
repo_ingestor-0.1.2.dist-info/METADATA
repo_ingestor-0.1.2.dist-info/WHEEL
repo_ingestor-0.1.2.dist-info/entry_points.txt
repo_ingestor-0.1.2.dist-info/top_level.txt
repo_ingestor-0.1.2.dist-info/RECORD
